libdata/__init__.py
libdata/models/__init__.py
libdata/models/enums.py
libdata/models/importer.py
libdata/models/tables.py
libdata/settings.py
df_data_lib-0.0.13.dist-info/WHEEL
df_data_lib-0.0.13.dist-info/METADATA
df_data_lib-0.0.13.dist-info/RECORD
