Metadata-Version: 2.1
Name: df-data-lib
Version: 0.0.13
Summary: 
Author: sufyanaligit
Author-email: informsufyan@gmail.com
Requires-Python: >=3.10,<4.0
Classifier: Programming Language :: Python :: 3
Classifier: Programming Language :: Python :: 3.10
Requires-Dist: Jinja2 (>=3.1.2,<4.0.0)
Requires-Dist: SQLAlchemy (>=1.4.39,<2.0.0)
Requires-Dist: SQLAlchemy-Utils (>=0.38.3,<0.39.0)
Requires-Dist: alembic (>=1.8.1,<2.0.0)
Requires-Dist: artifacts-keyring (>=0.3.2,<0.4.0)
Requires-Dist: asyncpg (>=0.26.0,<0.27.0)
Requires-Dist: click (>=8.1.3,<9.0.0)
Requires-Dist: coverage (>=6.4.2,<7.0.0)
Requires-Dist: fastapi (>=0.79.0,<0.80.0)
Requires-Dist: ipython (>=8.4.0,<9.0.0)
Requires-Dist: jsql (>=0.8,<0.9)
Requires-Dist: keyring (>=23.8.2,<24.0.0)
Requires-Dist: mangum (>=0.15.1,<0.16.0)
Requires-Dist: psycopg2-binary (>=2.9.3,<3.0.0)
Requires-Dist: pydantic[email] (>=1.9.2,<2.0.0)
Requires-Dist: pylint (>=2.15.0,<3.0.0)
Requires-Dist: pytest (>=7.1.2,<8.0.0)
Requires-Dist: pytest-azurepipelines (>=1.0.3,<2.0.0)
Requires-Dist: pytest-bdd (>=6.0.1,<7.0.0)
Requires-Dist: pytest-cov (>=3.0.0,<4.0.0)
Requires-Dist: pytest-mock (>=3.8.2,<4.0.0)
Requires-Dist: requests (>=2.28.1,<3.0.0)
Requires-Dist: setuptools (>=65.3.0,<66.0.0)
Requires-Dist: uvicorn (>=0.18.2,<0.19.0)
